LICENSE.txt
MANIFEST.in
README.md
requirements.txt
setup.py
bioscrape_cobra/LacOperon_deterministic.xml
bioscrape_cobra/LacOperon_stochastic.xml
bioscrape_cobra/__init__.py
bioscrape_cobra/bioscrape_cobra_deterministic.py
bioscrape_cobra/bioscrape_cobra_stochastic.py
bioscrape_cobra/flux_adaptor.py
bioscrape_cobra/generate_figure.py
bioscrape_cobra/plot.py
bioscrape_cobra/simulate.py
bioscrape_cobra/temp_sbml_file.xml
vivarium_notebooks.egg-info/PKG-INFO
vivarium_notebooks.egg-info/SOURCES.txt
vivarium_notebooks.egg-info/dependency_links.txt
vivarium_notebooks.egg-info/entry_points.txt
vivarium_notebooks.egg-info/requires.txt
vivarium_notebooks.egg-info/top_level.txt