Metadata-Version: 2.1
Name: vivarium-notebooks
Version: 0.0.5
Summary: UNKNOWN
Home-page: https://github.com/vivarium-collective/vivarium-notebooks
Author: Eran Agmon, William Poole
Author-email: agmon.eran@gmail.com, wpoole@caltech.edu
License: MIT
Platform: UNKNOWN
